patternlib/__init__.py
patternlib/alphabets/__init__.py
patternlib/alphabets/a_pattern.py
patternlib/alphabets/e_pattern.py
patternlib/alphabets/f_pattern.py
patternlib/alphabets/h_pattern.py
patternlib/alphabets/i_pattern.py
patternlib/alphabets/l_pattern.py
patternlib/alphabets/t_pattern.py
patternlib/alphabets/v_pattern.py
patternlib/alphabets/x_pattern.py
patternlib/alphabets/z_pattern.py
patternlib/constants/__init__.py
patternlib/constants/patternlib_constants.py
patternlib/shapes/__init__.py
patternlib/shapes/diamond/__init__.py
patternlib/shapes/diamond/hollow_diamond.py
patternlib/shapes/diamond/narrow_diamond.py
patternlib/shapes/diamond/narrow_string_diamond.py
patternlib/shapes/diamond/wide_diamond.py
patternlib/shapes/diamond/wide_string_diamond.py
patternlib/shapes/hour_glass/__init__.py
patternlib/shapes/hour_glass/hollow_hour_glass.py
patternlib/shapes/hour_glass/horizontal_hour_glass.py
patternlib/shapes/hour_glass/horizontal_hour_glass_common_midpoint.py
patternlib/shapes/hour_glass/hour_glass.py
patternlib/shapes/hour_glass/string_hour_glass.py
patternlib/shapes/miscellaneous/__init__.py
patternlib/shapes/miscellaneous/inverted_number_7.py
patternlib/shapes/miscellaneous/inverted_sigma.py
patternlib/shapes/miscellaneous/inverted_z.py
patternlib/shapes/miscellaneous/number_7.py
patternlib/shapes/miscellaneous/pyramid_diamond.py
patternlib/shapes/miscellaneous/pyramid_hour_glass.py
patternlib/shapes/miscellaneous/sigma.py
patternlib/shapes/pyramid/__init__.py
patternlib/shapes/pyramid/decreasing_number_pyramid_pointing_down.py
patternlib/shapes/pyramid/decreasing_number_pyramid_pointing_up.py
patternlib/shapes/pyramid/hollow_pyramid_pointing_down.py
patternlib/shapes/pyramid/hollow_pyramid_pointing_up.py
patternlib/shapes/pyramid/increasing_number_pyramid_pointing_down.py
patternlib/shapes/pyramid/increasing_number_pyramid_pointing_up.py
patternlib/shapes/pyramid/pyramid_pointing_down.py
patternlib/shapes/pyramid/pyramid_pointing_up.py
patternlib-1.1.4.dist-info/LICENSE
patternlib-1.1.4.dist-info/METADATA
patternlib-1.1.4.dist-info/WHEEL
patternlib-1.1.4.dist-info/top_level.txt
patternlib-1.1.4.dist-info/RECORD
